eks_switcher/__init__.py
eks_switcher/__main__.py
eks_switcher/aws_config.py
eks_switcher/aws_eks.py
eks_switcher/kube_config.py
eks_switcher/files/config.jinja2
eks_switcher-0.6.dist-info/entry_points.txt
eks_switcher-0.6.dist-info/LICENSE
eks_switcher-0.6.dist-info/WHEEL
eks_switcher-0.6.dist-info/METADATA
eks_switcher-0.6.dist-info/RECORD
